{
  "totalErrors": 2,
  "errorsByType": {
    "error": [
      "Warning: React does not recognize the `%s` prop on a DOM element. If you intentionally want it to appear in the DOM as a custom attribute, spell it as lowercase `%s` instead. If you accidentally passed it from a parent component, remove it from the DOM element.%s fetchPriority fetchpriority \n    at img\n    at div\n    at div\n    at div\n    at _c (http://localhost:8080/src/components/ui/card.tsx:23:53)\n    at div\n    at div\n    at http://localhost:8080/node_modules/.vite/deps/chunk-F4P7PQYJ.js?v=358a45d3:43:13\n    at Presence (http://localhost:8080/node_modules/.vite/deps/chunk-FD2JVFQ7.js?v=358a45d3:24:11)\n    at http://localhost:8080/node_modules/.vite/deps/@radix-ui_react-tabs.js?v=358a45d3:393:13\n    at _c6 (http://localhost:8080/src/components/ui/tabs.tsx:130:61)\n    at div\n    at http://localhost:8080/node_modules/.vite/deps/chunk-F4P7PQYJ.js?v=358a45d3:43:13\n    at Provider (http://localhost:8080/node_modules/.vite/deps/chunk-3RXG37ZK.js?v=358a45d3:38:15)\n    at http://localhost:8080/node_modules/.vite/deps/@radix-ui_react-tabs.js?v=358a45d3:270:7\n    at http://localhost:8080/src/components/ui/tabs.tsx:27:60\n    at div\n    at GamesBrowser (http://localhost:8080/src/pages/GamesBrowser.tsx:120:22)\n    at div\n    at div\n    at Layout (http://localhost:8080/src/components/Layout.tsx:30:19)\n    at RenderedRoute (http://localhost:8080/node_modules/.vite/deps/react-router-dom.js?v=358a45d3:4088:5)\n    at Routes (http://localhost:8080/node_modules/.vite/deps/react-router-dom.js?v=358a45d3:4558:5)\n    at Suspense\n    at Router (http://localhost:8080/node_modules/.vite/deps/react-router-dom.js?v=358a45d3:4501:15)\n    at BrowserRouter (http://localhost:8080/node_modules/.vite/deps/react-router-dom.js?v=358a45d3:5247:5)\n    at HelpGuideProvider (http://localhost:8080/src/hooks/useHelpGuide.tsx:26:37)\n    at Provider (http://localhost:8080/node_modules/.vite/deps/chunk-3RXG37ZK.js?v=358a45d3:38:15)\n    at TooltipProvider (http://localhost:8080/node_modules/.vite/deps/@radix-ui_react-tooltip.js?v=358a45d3:65:5)\n    at PerformanceWrapper (http://localhost:8080/src/components/PerformanceWrapper.tsx:24:31)\n    at FullscreenProvider (http://localhost:8080/src/contexts/FullscreenContext.tsx:25:38)\n    at ThemeProvider (http://localhost:8080/src/contexts/ThemeContext.tsx:26:33)\n    at AchievementProvider (http://localhost:8080/src/contexts/AchievementContext.tsx:25:39)\n    at TournamentProvider (http://localhost:8080/src/contexts/TournamentContext.tsx:31:38)\n    at BracketProvider (http://localhost:8080/src/contexts/BracketContext.tsx:25:35)\n    at AuthProvider (http://localhost:8080/src/hooks/useAuth.tsx:26:32)\n    at QueryClientProvider (http://localhost:8080/node_modules/.vite/deps/@tanstack_react-query.js?v=358a45d3:3022:3)\n    at App",
      "Warning: Unexpected return value from a callback ref in %s. A callback ref should not return a function.%s div \n    at div\n    at _c (http://localhost:8080/src/components/ui/card.tsx:23:53)\n    at div\n    at div\n    at http://localhost:8080/node_modules/.vite/deps/chunk-F4P7PQYJ.js?v=358a45d3:43:13\n    at Presence (http://localhost:8080/node_modules/.vite/deps/chunk-FD2JVFQ7.js?v=358a45d3:24:11)\n    at http://localhost:8080/node_modules/.vite/deps/@radix-ui_react-tabs.js?v=358a45d3:393:13\n    at _c6 (http://localhost:8080/src/components/ui/tabs.tsx:130:61)\n    at div\n    at http://localhost:8080/node_modules/.vite/deps/chunk-F4P7PQYJ.js?v=358a45d3:43:13\n    at Provider (http://localhost:8080/node_modules/.vite/deps/chunk-3RXG37ZK.js?v=358a45d3:38:15)\n    at http://localhost:8080/node_modules/.vite/deps/@radix-ui_react-tabs.js?v=358a45d3:270:7\n    at http://localhost:8080/src/components/ui/tabs.tsx:27:60\n    at div\n    at GamesBrowser (http://localhost:8080/src/pages/GamesBrowser.tsx:120:22)\n    at div\n    at div\n    at Layout (http://localhost:8080/src/components/Layout.tsx:30:19)\n    at RenderedRoute (http://localhost:8080/node_modules/.vite/deps/react-router-dom.js?v=358a45d3:4088:5)\n    at Routes (http://localhost:8080/node_modules/.vite/deps/react-router-dom.js?v=358a45d3:4558:5)\n    at Suspense\n    at Router (http://localhost:8080/node_modules/.vite/deps/react-router-dom.js?v=358a45d3:4501:15)\n    at BrowserRouter (http://localhost:8080/node_modules/.vite/deps/react-router-dom.js?v=358a45d3:5247:5)\n    at HelpGuideProvider (http://localhost:8080/src/hooks/useHelpGuide.tsx:26:37)\n    at Provider (http://localhost:8080/node_modules/.vite/deps/chunk-3RXG37ZK.js?v=358a45d3:38:15)\n    at TooltipProvider (http://localhost:8080/node_modules/.vite/deps/@radix-ui_react-tooltip.js?v=358a45d3:65:5)\n    at PerformanceWrapper (http://localhost:8080/src/components/PerformanceWrapper.tsx:24:31)\n    at FullscreenProvider (http://localhost:8080/src/contexts/FullscreenContext.tsx:25:38)\n    at ThemeProvider (http://localhost:8080/src/contexts/ThemeContext.tsx:26:33)\n    at AchievementProvider (http://localhost:8080/src/contexts/AchievementContext.tsx:25:39)\n    at TournamentProvider (http://localhost:8080/src/contexts/TournamentContext.tsx:31:38)\n    at BracketProvider (http://localhost:8080/src/contexts/BracketContext.tsx:25:35)\n    at AuthProvider (http://localhost:8080/src/hooks/useAuth.tsx:26:32)\n    at QueryClientProvider (http://localhost:8080/node_modules/.vite/deps/@tanstack_react-query.js?v=358a45d3:3022:3)\n    at App"
    ]
  },
  "redefinitions": [],
  "allErrors": [
    {
      "type": "error",
      "text": "Warning: React does not recognize the `%s` prop on a DOM element. If you intentionally want it to appear in the DOM as a custom attribute, spell it as lowercase `%s` instead. If you accidentally passed it from a parent component, remove it from the DOM element.%s fetchPriority fetchpriority \n    at img\n    at div\n    at div\n    at div\n    at _c (http://localhost:8080/src/components/ui/card.tsx:23:53)\n    at div\n    at div\n    at http://localhost:8080/node_modules/.vite/deps/chunk-F4P7PQYJ.js?v=358a45d3:43:13\n    at Presence (http://localhost:8080/node_modules/.vite/deps/chunk-FD2JVFQ7.js?v=358a45d3:24:11)\n    at http://localhost:8080/node_modules/.vite/deps/@radix-ui_react-tabs.js?v=358a45d3:393:13\n    at _c6 (http://localhost:8080/src/components/ui/tabs.tsx:130:61)\n    at div\n    at http://localhost:8080/node_modules/.vite/deps/chunk-F4P7PQYJ.js?v=358a45d3:43:13\n    at Provider (http://localhost:8080/node_modules/.vite/deps/chunk-3RXG37ZK.js?v=358a45d3:38:15)\n    at http://localhost:8080/node_modules/.vite/deps/@radix-ui_react-tabs.js?v=358a45d3:270:7\n    at http://localhost:8080/src/components/ui/tabs.tsx:27:60\n    at div\n    at GamesBrowser (http://localhost:8080/src/pages/GamesBrowser.tsx:120:22)\n    at div\n    at div\n    at Layout (http://localhost:8080/src/components/Layout.tsx:30:19)\n    at RenderedRoute (http://localhost:8080/node_modules/.vite/deps/react-router-dom.js?v=358a45d3:4088:5)\n    at Routes (http://localhost:8080/node_modules/.vite/deps/react-router-dom.js?v=358a45d3:4558:5)\n    at Suspense\n    at Router (http://localhost:8080/node_modules/.vite/deps/react-router-dom.js?v=358a45d3:4501:15)\n    at BrowserRouter (http://localhost:8080/node_modules/.vite/deps/react-router-dom.js?v=358a45d3:5247:5)\n    at HelpGuideProvider (http://localhost:8080/src/hooks/useHelpGuide.tsx:26:37)\n    at Provider (http://localhost:8080/node_modules/.vite/deps/chunk-3RXG37ZK.js?v=358a45d3:38:15)\n    at TooltipProvider (http://localhost:8080/node_modules/.vite/deps/@radix-ui_react-tooltip.js?v=358a45d3:65:5)\n    at PerformanceWrapper (http://localhost:8080/src/components/PerformanceWrapper.tsx:24:31)\n    at FullscreenProvider (http://localhost:8080/src/contexts/FullscreenContext.tsx:25:38)\n    at ThemeProvider (http://localhost:8080/src/contexts/ThemeContext.tsx:26:33)\n    at AchievementProvider (http://localhost:8080/src/contexts/AchievementContext.tsx:25:39)\n    at TournamentProvider (http://localhost:8080/src/contexts/TournamentContext.tsx:31:38)\n    at BracketProvider (http://localhost:8080/src/contexts/BracketContext.tsx:25:35)\n    at AuthProvider (http://localhost:8080/src/hooks/useAuth.tsx:26:32)\n    at QueryClientProvider (http://localhost:8080/node_modules/.vite/deps/@tanstack_react-query.js?v=358a45d3:3022:3)\n    at App",
      "timestamp": 1759992486526
    },
    {
      "type": "error",
      "text": "Warning: Unexpected return value from a callback ref in %s. A callback ref should not return a function.%s div \n    at div\n    at _c (http://localhost:8080/src/components/ui/card.tsx:23:53)\n    at div\n    at div\n    at http://localhost:8080/node_modules/.vite/deps/chunk-F4P7PQYJ.js?v=358a45d3:43:13\n    at Presence (http://localhost:8080/node_modules/.vite/deps/chunk-FD2JVFQ7.js?v=358a45d3:24:11)\n    at http://localhost:8080/node_modules/.vite/deps/@radix-ui_react-tabs.js?v=358a45d3:393:13\n    at _c6 (http://localhost:8080/src/components/ui/tabs.tsx:130:61)\n    at div\n    at http://localhost:8080/node_modules/.vite/deps/chunk-F4P7PQYJ.js?v=358a45d3:43:13\n    at Provider (http://localhost:8080/node_modules/.vite/deps/chunk-3RXG37ZK.js?v=358a45d3:38:15)\n    at http://localhost:8080/node_modules/.vite/deps/@radix-ui_react-tabs.js?v=358a45d3:270:7\n    at http://localhost:8080/src/components/ui/tabs.tsx:27:60\n    at div\n    at GamesBrowser (http://localhost:8080/src/pages/GamesBrowser.tsx:120:22)\n    at div\n    at div\n    at Layout (http://localhost:8080/src/components/Layout.tsx:30:19)\n    at RenderedRoute (http://localhost:8080/node_modules/.vite/deps/react-router-dom.js?v=358a45d3:4088:5)\n    at Routes (http://localhost:8080/node_modules/.vite/deps/react-router-dom.js?v=358a45d3:4558:5)\n    at Suspense\n    at Router (http://localhost:8080/node_modules/.vite/deps/react-router-dom.js?v=358a45d3:4501:15)\n    at BrowserRouter (http://localhost:8080/node_modules/.vite/deps/react-router-dom.js?v=358a45d3:5247:5)\n    at HelpGuideProvider (http://localhost:8080/src/hooks/useHelpGuide.tsx:26:37)\n    at Provider (http://localhost:8080/node_modules/.vite/deps/chunk-3RXG37ZK.js?v=358a45d3:38:15)\n    at TooltipProvider (http://localhost:8080/node_modules/.vite/deps/@radix-ui_react-tooltip.js?v=358a45d3:65:5)\n    at PerformanceWrapper (http://localhost:8080/src/components/PerformanceWrapper.tsx:24:31)\n    at FullscreenProvider (http://localhost:8080/src/contexts/FullscreenContext.tsx:25:38)\n    at ThemeProvider (http://localhost:8080/src/contexts/ThemeContext.tsx:26:33)\n    at AchievementProvider (http://localhost:8080/src/contexts/AchievementContext.tsx:25:39)\n    at TournamentProvider (http://localhost:8080/src/contexts/TournamentContext.tsx:31:38)\n    at BracketProvider (http://localhost:8080/src/contexts/BracketContext.tsx:25:35)\n    at AuthProvider (http://localhost:8080/src/hooks/useAuth.tsx:26:32)\n    at QueryClientProvider (http://localhost:8080/node_modules/.vite/deps/@tanstack_react-query.js?v=358a45d3:3022:3)\n    at App",
      "timestamp": 1759992486533
    }
  ]
}